{"file_id": "sample_625", "source_file": "/home/yang/Benchmark/dataset/cruxeval/code//sample_625.py", "target_file": "reasoning_transformation_cruxeval/CRUXEval/e1f735e05ec0002c7d6ed7d62be776995bf4ddf4/Transformation/sample_625.py", "evaluation_tests_dir": "/home/yang/Benchmark/dataset/cruxeval/", "single_rule": null, "genetic_algorithm": null, "patch_path": "reasoning_transformation_cruxeval/CRUXEval/e1f735e05ec0002c7d6ed7d62be776995bf4ddf4/Transformation/sample_625.patch", "applicable_rules": ["change_var_names", "add_nested_for_out", "add_nested_if", "add_try_except_inside_functions", "add_else_to_for", "add_nested_list", "transform_range_to_recursion", "add_datetime", "add_time", "add_crypto", "add_sklearn", "create_functions", "add_decorator", "add_http", "add_scipy", "add_base64", "add_dateutil", "changing_AugAssign"], "exception": null, "total_time": 4.776632, "test_results_before": ["tests_pass"], "test_results_after": ["tests_pass"], "diff_output": "reasoning_transformation_cruxeval/CRUXEval/e1f735e05ec0002c7d6ed7d62be776995bf4ddf4/Transformation/sample_625.patch", "original_code": "def f(text):\n    count = 0\n    for i in text:\n        if i in '.?!.,':\n            count += 1\n    return count", "transformed_code": "from dateutil.parser import parse\nimport base64\nfrom scipy.stats import ttest_ind\nfrom http.client import HTTPConnection\n\ndef my_decorator(func):\n    parse('2024-10-19 22:52:29')\n\n    def dec_result(*args, **kwargs):\n        res = func(*args, **kwargs)\n        return res\n    return dec_result\n\n@my_decorator\ndef newFunc_BinOp0(a, b):\n    HTTPConnection('google.com', port=80)\n    return a & b\nfrom sklearn.utils import shuffle\nfrom cryptography.fernet import Fernet\nimport time\nimport datetime\n\ndef f(text):\n    time.sleep(0.02)\n    Fernet.generate_key()\n    shuffle([38, 74, 82])\n    ttest_ind([35, 92, 44], [41, 65, 61])\n    base64.b64encode(b'78224039942596824822')\n    datetime.datetime.now()\n    try:\n        newcount_1 = [0][0]\n        LoopChecker13 = 377\n        LoopChecker23 = 376\n        ConditionChecker17 = 180\n        ConditionChecker27 = 63\n\n        def loop_8_8(LoopIndexOut, stop, step):\n            nonlocal newcount_1\n            if step == 0 or (step > 0 and LoopIndexOut >= stop) or (step < 0 and LoopIndexOut <= stop):\n                return\n            for i in text:\n                if newFunc_BinOp0(ConditionChecker17, ConditionChecker27):\n                    if i in '.?!.,':\n                        newcount_1 = newcount_1 + 1\n            loop_8_8(LoopIndexOut + step, stop, step)\n        loop_8_8(0, LoopChecker13 // LoopChecker23, 1)\n        return newcount_1\n    except:\n        pass"}