{"file_id": "sample_355", "source_file": "/home/yang/Benchmark/dataset/cruxeval/code//sample_355.py", "target_file": "reasoning_transformation_cruxeval/CRUXEval/e1f735e05ec0002c7d6ed7d62be776995bf4ddf4/Transformation/sample_355.py", "evaluation_tests_dir": "/home/yang/Benchmark/dataset/cruxeval/", "single_rule": null, "genetic_algorithm": null, "patch_path": "reasoning_transformation_cruxeval/CRUXEval/e1f735e05ec0002c7d6ed7d62be776995bf4ddf4/Transformation/sample_355.patch", "applicable_rules": ["add_try_except_inside_functions", "add_datetime", "add_time", "add_crypto", "add_sklearn", "add_decorator", "add_http", "add_scipy", "add_base64", "add_dateutil"], "exception": null, "total_time": 5.143612, "test_results_before": ["tests_pass"], "test_results_after": ["tests_pass"], "diff_output": "reasoning_transformation_cruxeval/CRUXEval/e1f735e05ec0002c7d6ed7d62be776995bf4ddf4/Transformation/sample_355.patch", "original_code": "def f(text, prefix):\n    return text[len(prefix):]", "transformed_code": "from dateutil.parser import parse\nimport base64\nfrom scipy.stats import ttest_ind\nfrom http.client import HTTPConnection\n\ndef my_decorator(func):\n    ttest_ind([96, 5, 10], [76, 1, 48])\n\n    def dec_result(*args, **kwargs):\n        res = func(*args, **kwargs)\n        return res\n    parse('2024-10-19 22:22:43')\n    return dec_result\nfrom sklearn.utils import shuffle\nfrom cryptography.fernet import Fernet\nimport time\nimport datetime\n\n@my_decorator\ndef f(text, prefix):\n    HTTPConnection('google.com', port=80)\n    shuffle([3, 10, 29])\n    datetime.datetime.now()\n    base64.b64encode(b'89290455871221763177')\n    Fernet.generate_key()\n    time.sleep(0.18)\n    try:\n        return text[len(prefix):]\n    except:\n        pass"}