{"file_id": "sample_629", "source_file": "/home/yang/Benchmark/dataset/cruxeval/code//sample_629.py", "target_file": "reasoning_transformation_cruxeval/CRUXEval/e1f735e05ec0002c7d6ed7d62be776995bf4ddf4/Transformation/sample_629.py", "evaluation_tests_dir": "/home/yang/Benchmark/dataset/cruxeval/", "single_rule": null, "genetic_algorithm": null, "patch_path": "reasoning_transformation_cruxeval/CRUXEval/e1f735e05ec0002c7d6ed7d62be776995bf4ddf4/Transformation/sample_629.patch", "applicable_rules": ["add_nested_if", "add_try_except_inside_functions", "add_nested_list", "add_datetime", "add_time", "add_crypto", "add_sklearn", "create_functions", "add_decorator", "add_http", "add_scipy", "add_base64", "add_dateutil"], "exception": null, "total_time": 4.413773, "test_results_before": ["tests_pass"], "test_results_after": ["tests_pass"], "diff_output": "reasoning_transformation_cruxeval/CRUXEval/e1f735e05ec0002c7d6ed7d62be776995bf4ddf4/Transformation/sample_629.patch", "original_code": "def f(text, dng):\n    if dng not in text:\n        return text\n    if text[-len(dng):] == dng:\n        return text[:-len(dng)]\n    return text[:-1] + f(text[:-2], dng)", "transformed_code": "from dateutil.parser import parse\nimport base64\nfrom scipy.stats import ttest_ind\nfrom http.client import HTTPConnection\n\ndef my_decorator(func):\n    HTTPConnection('google.com', port=80)\n    parse('2024-10-19 22:52:51')\n\n    def dec_result(*args, **kwargs):\n        res = func(*args, **kwargs)\n        return res\n    return dec_result\n\n@my_decorator\ndef newFunc_23881(arg0, arg1):\n    ttest_ind([4, 79, 6], [69, 47, 41])\n    base64.b64encode(b'56866954871938947531')\n    return arg0 + arg1\nfrom sklearn.utils import shuffle\nfrom cryptography.fernet import Fernet\nimport time\nimport datetime\n\ndef f(text, dng):\n    datetime.datetime.now()\n    Fernet.generate_key()\n    time.sleep(0.0)\n    shuffle([86, 76, 12])\n    try:\n        ConditionChecker12 = [329][0]\n        ConditionChecker22 = 194\n        if ConditionChecker12 & ConditionChecker22:\n            if dng not in text:\n                return text\n        if text[-len(dng):] == dng:\n            return text[:-len(dng)]\n        return newFunc_23881(text[:-1], f(text[:-2], dng))\n    except:\n        pass"}