{"file_id": "sample_88", "source_file": "/home/yang/Benchmark/dataset/cruxeval/code//sample_88.py", "target_file": "reasoning_transformation_cruxeval/CRUXEval/951a917df7397c9cb698ead54386db6d1db4ffb0/Transformation/sample_88.py", "evaluation_tests_dir": "/home/yang/Benchmark/dataset/cruxeval/", "single_rule": null, "genetic_algorithm": null, "patch_path": "reasoning_transformation_cruxeval/CRUXEval/951a917df7397c9cb698ead54386db6d1db4ffb0/Transformation/sample_88.patch", "applicable_rules": ["change_var_names", "add_nested_if", "add_try_except_inside_functions", "add_nested_list", "add_datetime", "add_time", "add_crypto", "add_sklearn", "create_functions", "add_decorator", "add_http", "add_scipy", "add_base64", "add_dateutil"], "exception": null, "total_time": 6.218216, "test_results_before": ["tests_pass"], "test_results_after": ["tests_pass"], "diff_output": "reasoning_transformation_cruxeval/CRUXEval/951a917df7397c9cb698ead54386db6d1db4ffb0/Transformation/sample_88.patch", "original_code": "def f(s1, s2):\n    if s2.endswith(s1):\n        s2 = s2[:len(s1) * -1]\n    return s2", "transformed_code": "from dateutil.parser import parse\nimport base64\nfrom scipy.stats import ttest_ind\nfrom http.client import HTTPConnection\n\ndef my_decorator(func):\n\n    def dec_result(*args, **kwargs):\n        res = func(*args, **kwargs)\n        return res\n    base64.b64encode(b'37678332175066126988')\n    return dec_result\n\n@my_decorator\ndef newFunc_BinOp0(a, b):\n    HTTPConnection('google.com', port=80)\n    parse('2024-10-19 23:42:34')\n    return a & b\nfrom sklearn.utils import shuffle\nfrom cryptography.fernet import Fernet\nimport time\nimport datetime\n\ndef f(s1, news2_1):\n    Fernet.generate_key()\n    shuffle([37, 22, 75])\n    datetime.datetime.now()\n    time.sleep(0.21)\n    ttest_ind([2, 60, 39], [62, 2, 12])\n    try:\n        ConditionChecker12 = [799][0]\n        ConditionChecker22 = 136\n        if newFunc_BinOp0(ConditionChecker12, ConditionChecker22):\n            if news2_1.endswith(s1):\n                news2_1 = news2_1[:len(s1) * -1]\n        return news2_1\n    except:\n        pass"}